napalm_unifi/__init__.py
napalm_unifi/uap.py
napalm_unifi/unifi.py
napalm_unifi/usg.py
napalm_unifi/usw.py
napalm_unifi/usw_flex.py
napalm_unifi/usw_lite.py
napalm_unifi/utils/__init__.py
napalm_unifi/utils/textfsm_templates/__init__.py
napalm_unifi/utils/textfsm_templates/index
napalm_unifi/utils/textfsm_templates/ubiquiti_unifi_ip_address_show.textfsm
napalm_unifi/utils/textfsm_templates/ubiquiti_unifi_ip_link_show.textfsm
napalm_unifi/utils/textfsm_templates/ubiquiti_unifi_show_lldp_interfaces_all_neighbor.textfsm
napalm_unifi/utils/textfsm_templates/ubiquiti_unifi_show_lldp_neighbor.textfsm
napalm_unifi/utils/textfsm_templates/ubiquiti_unifi_show_lldp_remote-device_all.textfsm
napalm_unifi/utils/textfsm_templates/ubiquiti_unifi_show_lldp_remote-device_detail.textfsm
napalm_unifi-0.3.1.dist-info/LICENSE
napalm_unifi-0.3.1.dist-info/METADATA
napalm_unifi-0.3.1.dist-info/WHEEL
napalm_unifi-0.3.1.dist-info/RECORD
