Metadata-Version: 2.1
Name: napalm-unifi
Version: 0.3.1
Summary: 
License: Apache 2.0
Author: Andrew Bates
Author-email: andrew.bates@networktocode.com
Requires-Python: >=3.9,<4.0
Classifier: License :: Other/Proprietary License
Classifier: Programming Language :: Python :: 3
Classifier: Programming Language :: Python :: 3.9
Classifier: Programming Language :: Python :: 3.10
Classifier: Programming Language :: Python :: 3.11
Classifier: Programming Language :: Python :: 3.12
Requires-Dist: napalm (>=4.1.0,<5.0.0)
